MANIFEST.in
README.md
conf.py
setup.py
version.py
dstream_excel/__init__.py
dstream_excel/fileops.py
dstream_excel/main.py
dstream_excel.egg-info/PKG-INFO
dstream_excel.egg-info/SOURCES.txt
dstream_excel.egg-info/dependency_links.txt
dstream_excel.egg-info/requires.txt
dstream_excel.egg-info/top_level.txt
dstream_excel/dstream/__init__.py
dstream_excel/dstream/combine.py
dstream_excel/dstream/downloader.py
dstream_excel/dstream/keepopen/__init__.py
dstream_excel/dstream/keepopen/combine.py
dstream_excel/dstream/keepopen/download.py
dstream_excel/dstream/keepopen/excel.py
dstream_excel/dstream/keepopen/extract.py
dstream_excel/dstream/keepopen/wait.py
dstream_excel/dstream/workbook/__init__.py
dstream_excel/dstream/workbook/create.py
dstream_excel/dstream/workbook/exceptions.py
dstream_excel/dstream/workbook/filename.py
dstream_excel/dstream/workbook/functions.py
dstream_excel/dstream/workbook/populate.py
dstream_excel/dstream/workbook/wait.py
dstream_excel/tools/__init__.py
dstream_excel/tools/ext_pandas.py
dstream_excel/tracker/__init__.py
dstream_excel/tracker/files.py
dstream_excel/tracker/timing.py