Metadata-Version: 1.2
Name: dstream-excel
Version: 0.4.0
Summary: Automate data collection from Thompson Reuters Datastream using the excel plugin
Home-page: https://github.com/whoopnip/datastream-excel-downloader-py
Author: Nick DeRobertis
Author-email: whoopnip@gmail.com
License: MIT
Project-URL: Code, https://github.com/whoopnip/datastream-excel-downloader-py
Project-URL: Documentation, https://whoopnip.github.io/datastream-excel-downloader-py/
Platform: UNKNOWN
Classifier: Development Status :: 3 - Alpha
Classifier: Intended Audience :: Developers
Classifier: Programming Language :: Python :: 3.6
Classifier: Programming Language :: Python :: 3.7
Classifier: Operating System :: Microsoft :: Windows
